subhajit_engg_tools/__init__.py
subhajit_engg_tools/main.py
subhajit_engg_tools/connectors/__init__.py
subhajit_engg_tools/connectors/postgres.py
subhajit_engg_tools/connectors/snowflake.py
subhajit_engg_tools/smarthome/__init__.py
subhajit_engg_tools/smarthome/tuya.py
subhajit_engg_tools-1.1.4.dist-info/LICENSE
subhajit_engg_tools-1.1.4.dist-info/METADATA
subhajit_engg_tools-1.1.4.dist-info/WHEEL
subhajit_engg_tools-1.1.4.dist-info/top_level.txt
subhajit_engg_tools-1.1.4.dist-info/RECORD
