Metadata-Version: 2.1
Name: subhajit_engg_tools
Version: 1.1.4
Summary: Useful data engineering tools
Home-page: https://github.com/subhajitsr/subhajit-engineering-tools
Author: Subhajit Maji
Author-email: subhajitsr@gmail.com
License: UNKNOWN
Project-URL: Bug Tracker, https://github.com/subhajitsr/subhajit-engineering-tools
Platform: UNKNOWN
Classifier: Programming Language :: Python :: 3
Classifier: License :: OSI Approved :: MIT License
Classifier: Operating System :: OS Independent
Requires-Python: >=3.6
License-File: LICENSE
